af_licence_manager/__init__.py
af_licence_manager/api_client.py
af_licence_manager/configuration.py
af_licence_manager/rest.py
af_licence_manager/api/__init__.py
af_licence_manager/api/arista_flow_service_api.py
af_licence_manager/api/default_api.py
af_licence_manager/api/licence_manager_api.py
af_licence_manager/models/__init__.py
af_licence_manager/models/abort_service_exception.py
af_licence_manager/models/abort_transaction_exception.py
af_licence_manager/models/agent_unknown_exception.py
af_licence_manager/models/authentication_exception.py
af_licence_manager/models/configuration_exception.py
af_licence_manager/models/data_consistency_exception.py
af_licence_manager/models/data_source_exception.py
af_licence_manager/models/dummy_parent.py
af_licence_manager/models/ebp_instance_reference.py
af_licence_manager/models/ilm_exception.py
af_licence_manager/models/ilm_exception_cause.py
af_licence_manager/models/ilm_exception_stack_trace.py
af_licence_manager/models/ilm_exception_suppressed.py
af_licence_manager/models/incompatible_gui_context_exception.py
af_licence_manager/models/interrupt_exception.py
af_licence_manager/models/invalid_activity_state_exception.py
af_licence_manager/models/invalid_data_container_exception.py
af_licence_manager/models/invalid_instance_state_exception.py
af_licence_manager/models/invalid_template_state_exception.py
af_licence_manager/models/licence_information.py
af_licence_manager/models/lock_exception.py
af_licence_manager/models/org_model_exception.py
af_licence_manager/models/parameter_exception.py
af_licence_manager/models/parameter_missing_exception.py
af_licence_manager/models/parameter_type_exception.py
af_licence_manager/models/password_policy_exception.py
af_licence_manager/models/plain_text_exception.py
af_licence_manager/models/policy_resolution_exception.py
af_licence_manager/models/qualified_agent.py
af_licence_manager/models/script_environment_exception.py
af_licence_manager/models/script_evaluation_exception.py
af_licence_manager-2.0.3.dist-info/LICENSE
af_licence_manager-2.0.3.dist-info/METADATA
af_licence_manager-2.0.3.dist-info/WHEEL
af_licence_manager-2.0.3.dist-info/top_level.txt
af_licence_manager-2.0.3.dist-info/RECORD
