Metadata-Version: 2.1
Name: af-licence-manager
Version: 2.0.3
Summary: AristaFlow BPM LicenceManager/LicenceManager REST Client
Home-page: UNKNOWN
Author: AristaFlow GmbH
Author-email: info@aristaflow.com
License: UNKNOWN
Keywords: Swagger,AristaFlowREST/LicenceManager
Platform: UNKNOWN
Requires-Dist: certifi
Requires-Dist: python-dateutil
Requires-Dist: six (>=1.10)
Requires-Dist: urllib3 (>=1.15)
